prototorch/__init__.py
prototorch/core/__init__.py
prototorch/core/competitions.py
prototorch/core/components.py
prototorch/core/distances.py
prototorch/core/initializers.py
prototorch/core/losses.py
prototorch/core/pooling.py
prototorch/core/similarities.py
prototorch/core/transforms.py
prototorch/datasets/__init__.py
prototorch/datasets/abstract.py
prototorch/datasets/sklearn.py
prototorch/datasets/spiral.py
prototorch/datasets/tecator.py
prototorch/datasets/xor.py
prototorch/nn/__init__.py
prototorch/nn/activations.py
prototorch/nn/wrappers.py
prototorch/utils/__init__.py
prototorch/utils/colors.py
prototorch/utils/utils.py
tests/__init__.py
tests/test_core.py
tests/test_datasets.py
tests/test_utils.py
prototorch-0.7.6.dist-info/LICENSE
prototorch-0.7.6.dist-info/METADATA
prototorch-0.7.6.dist-info/WHEEL
prototorch-0.7.6.dist-info/top_level.txt
prototorch-0.7.6.dist-info/RECORD
