Metadata-Version: 2.1
Name: prototorch
Version: 0.7.6
Summary: Highly extensible, GPU-supported Learning Vector Quantization (LVQ) toolbox built using PyTorch and its nn API.
Home-page: https://github.com/si-cim/prototorch
Download-URL: https://github.com/si-cim/prototorch.git
Author: Jensun Ravichandran
Author-email: jjensun@gmail.com
License: MIT
Classifier: Environment :: Console
Classifier: Natural Language :: English
Classifier: Development Status :: 4 - Beta
Classifier: Intended Audience :: Developers
Classifier: Intended Audience :: Education
Classifier: Intended Audience :: Science/Research
Classifier: Topic :: Scientific/Engineering :: Artificial Intelligence
Classifier: Topic :: Software Development :: Libraries
Classifier: Topic :: Software Development :: Libraries :: Python Modules
Classifier: License :: OSI Approved :: MIT License
Classifier: Operating System :: OS Independent
Classifier: Programming Language :: Python :: 3
Classifier: Programming Language :: Python :: 3.8
Classifier: Programming Language :: Python :: 3.9
Classifier: Programming Language :: Python :: 3.10
Classifier: Programming Language :: Python :: 3.11
Requires-Python: >=3.8
License-File: LICENSE
Requires-Dist: torch >=2.0.0
Requires-Dist: torchvision
Requires-Dist: numpy
Requires-Dist: scikit-learn
Requires-Dist: matplotlib
Provides-Extra: all
Requires-Dist: requests ; extra == 'all'
Requires-Dist: tqdm ; extra == 'all'
Requires-Dist: bump2version ; extra == 'all'
Requires-Dist: pre-commit ; extra == 'all'
Requires-Dist: recommonmark ; extra == 'all'
Requires-Dist: sphinx ; extra == 'all'
Requires-Dist: sphinx-rtd-theme ; extra == 'all'
Requires-Dist: sphinxcontrib-katex ; extra == 'all'
Requires-Dist: sphinx-autodoc-typehints ; extra == 'all'
Requires-Dist: torchinfo ; extra == 'all'
Requires-Dist: flake8 ; extra == 'all'
Requires-Dist: pytest ; extra == 'all'
Provides-Extra: datasets
Requires-Dist: requests ; extra == 'datasets'
Requires-Dist: tqdm ; extra == 'datasets'
Provides-Extra: dev
Requires-Dist: bump2version ; extra == 'dev'
Requires-Dist: pre-commit ; extra == 'dev'
Provides-Extra: docs
Requires-Dist: recommonmark ; extra == 'docs'
Requires-Dist: sphinx ; extra == 'docs'
Requires-Dist: sphinx-rtd-theme ; extra == 'docs'
Requires-Dist: sphinxcontrib-katex ; extra == 'docs'
Requires-Dist: sphinx-autodoc-typehints ; extra == 'docs'
Provides-Extra: examples
Requires-Dist: torchinfo ; extra == 'examples'
Provides-Extra: tests
Requires-Dist: flake8 ; extra == 'tests'
Requires-Dist: pytest ; extra == 'tests'
